<?xml version="1.0" ?>
<tv generator-info-name="clickthecity" generator-info-url="https://www.clickthecity.com">
  <channel id="a2z">
    <display-name>a2z</display-name>
  </channel>
  <channel id="anc">
    <display-name>anc</display-name>
  </channel>
  <channel id="animax">
    <display-name>animax</display-name>
  </channel>
  <channel id="axn">
    <display-name>axn</display-name>
  </channel>
  <channel id="cinema-one">
    <display-name>cinema-one</display-name>
  </channel>
  <channel id="gma">
    <display-name>gma</display-name>
  </channel>
  <channel id="gtv">
    <display-name>gtv</display-name>
  </channel>
  <channel id="ibc-tv-13">
    <display-name>ibc-tv-13</display-name>
  </channel>
  <channel id="jeepney-tv">
    <display-name>jeepney-tv</display-name>
  </channel>
  <channel id="kapamilya-channel">
    <display-name>kapamilya-channel</display-name>
  </channel>
  <channel id="net-25">
    <display-name>net-25</display-name>
  </channel>
  <channel id="pbo">
    <display-name>pbo</display-name>
  </channel>
  <channel id="ptv">
    <display-name>ptv</display-name>
  </channel>
  <channel id="solar-flix">
    <display-name>solar-flix</display-name>
  </channel>
  <channel id="tv5">
    <display-name>tv5</display-name>
  </channel>
  <channel id="viva-cinema">
    <display-name>viva-cinema</display-name>
  </channel>
  <programme channel="a2z" start="20260105100000 +0800" stop="20260105120000 +0800">
    <title>Zinema Sa Umaga</title>
  </programme>
  <programme channel="a2z" start="20260105120000 +0800" stop="20260105143000 +0800">
    <title>It's Showtime</title>
  </programme>
  <programme channel="a2z" start="20260105143000 +0800" stop="20260105151500 +0800">
    <title>Lavender Fields</title>
  </programme>
  <programme channel="a2z" start="20260105151500 +0800" stop="20260105160000 +0800">
    <title>Senior High</title>
  </programme>
  <programme channel="a2z" start="20260105160000 +0800" stop="20260105173000 +0800">
    <title>Afternoon Zinema</title>
  </programme>
  <programme channel="a2z" start="20260105173000 +0800" stop="20260105174500 +0800">
    <title>TV Patrol Express</title>
  </programme>
  <programme channel="a2z" start="20260105174500 +0800" stop="20260105183000 +0800">
    <title>Kapamilya Deal Or No Deal</title>
  </programme>
  <programme channel="a2z" start="20260105183000 +0800" stop="20260105200000 +0800">
    <title>TV Patrol</title>
  </programme>
  <programme channel="a2z" start="20260105200000 +0800" stop="20260105204500 +0800">
    <title>FPJ's Batang Quiapo</title>
  </programme>
  <programme channel="a2z" start="20260105204500 +0800" stop="20260105213000 +0800">
    <title>Roja</title>
  </programme>
  <programme channel="a2z" start="20260105213000 +0800" stop="20260105221500 +0800">
    <title>What Lies Beneath</title>
  </programme>
  <programme channel="a2z" start="20260105221500 +0800" stop="20260105224500 +0800">
    <title>Go Ahead</title>
  </programme>
  <programme channel="a2z" start="20260105224500 +0800" stop="20260105231500 +0800">
    <title>Balitang A2Z</title>
  </programme>
  <programme channel="a2z" start="20260105231500 +0800" stop="20260105234500 +0800">
    <title>Bro. Eddie Villanueva Classics</title>
  </programme>
  <programme channel="anc" start="20260105100000 +0800" stop="20260105103000 +0800">
    <title>Women of Style</title>
  </programme>
  <programme channel="anc" start="20260105103000 +0800" stop="20260105110000 +0800">
    <title>Hot Copy on Headstart with Karen Davila</title>
  </programme>
  <programme channel="anc" start="20260105110000 +0800" stop="20260105113000 +0800">
    <title>In Good Shape</title>
  </programme>
  <programme channel="anc" start="20260105113000 +0800" stop="20260105120000 +0800">
    <title>LSS: The Martin Nievera Show</title>
  </programme>
  <programme channel="anc" start="20260105120000 +0800" stop="20260105130000 +0800">
    <title>Dateline Philippines</title>
  </programme>
  <programme channel="anc" start="20260105130000 +0800" stop="20260105140000 +0800">
    <title>Foodprints</title>
  </programme>
  <programme channel="anc" start="20260105140000 +0800" stop="20260105143000 +0800">
    <title>Arts.21</title>
  </programme>
  <programme channel="anc" start="20260105143000 +0800" stop="20260105150000 +0800">
    <title>Mobil 1 The Grid</title>
  </programme>
  <programme channel="anc" start="20260105150000 +0800" stop="20260105160000 +0800">
    <title>Business Roadshow</title>
  </programme>
  <programme channel="anc" start="20260105160000 +0800" stop="20260105163000 +0800">
    <title>At The Moment</title>
  </programme>
  <programme channel="anc" start="20260105163000 +0800" stop="20260105170000 +0800">
    <title>Global 3000</title>
  </programme>
  <programme channel="anc" start="20260105170000 +0800" stop="20260105180000 +0800">
    <title>Top Story</title>
  </programme>
  <programme channel="anc" start="20260105180000 +0800" stop="20260105183000 +0800">
    <title>Executive Class</title>
  </programme>
  <programme channel="anc" start="20260105183000 +0800" stop="20260105200000 +0800">
    <title>TV Patrol</title>
  </programme>
  <programme channel="anc" start="20260105200000 +0800" stop="20260105203000 +0800">
    <title>Business Outlook</title>
  </programme>
  <programme channel="anc" start="20260105203000 +0800" stop="20260105210000 +0800">
    <title>Beyond The Exchange</title>
  </programme>
  <programme channel="anc" start="20260105210000 +0800" stop="20260105213000 +0800">
    <title>The World Tonight</title>
  </programme>
  <programme channel="anc" start="20260105213000 +0800" stop="20260105220000 +0800">
    <title>Executive Class</title>
  </programme>
  <programme channel="anc" start="20260105220000 +0800" stop="20260105223000 +0800">
    <title>Tomorrow Today</title>
  </programme>
  <programme channel="anc" start="20260105223000 +0800" stop="20260105230000 +0800">
    <title>Entrep Lab</title>
  </programme>
  <programme channel="anc" start="20260105230000 +0800" stop="20260106000000 +0800">
    <title>Beached</title>
  </programme>
  <programme channel="anc" start="20260106000000 +0800" stop="20260106003000 +0800">
    <title>The World Tonight</title>
  </programme>
  <programme channel="anc" start="20260106003000 +0800" stop="20260106010000 +0800">
    <title>At The Moment</title>
  </programme>
  <programme channel="anc" start="20260106010000 +0800" stop="20260106020000 +0800">
    <title>Headstart with Karen Davila</title>
  </programme>
  <programme channel="anc" start="20260106020000 +0800" stop="20260106023000 +0800">
    <title>EIC on The Move</title>
  </programme>
  <programme channel="anc" start="20260106023000 +0800" stop="20260106030000 +0800">
    <title>At The Moment</title>
  </programme>
  <programme channel="anc" start="20260106030000 +0800" stop="20260106033000 +0800">
    <title>Asian Air Safari</title>
  </programme>
  <programme channel="anc" start="20260106033000 +0800" stop="20260106040000 +0800">
    <title>Rev</title>
  </programme>
  <programme channel="anc" start="20260106040000 +0800" stop="20260106043000 +0800">
    <title>Women of Style</title>
  </programme>
  <programme channel="anc" start="20260106043000 +0800" stop="20260106050000 +0800">
    <title>Tomorrow Today</title>
  </programme>
  <programme channel="animax" start="20260105100000 +0800" stop="20260105110000 +0800">
    <title>Nyaight Of The Living Cat</title>
  </programme>
  <programme channel="animax" start="20260105110000 +0800" stop="20260105120000 +0800">
    <title>Wind Breaker</title>
  </programme>
  <programme channel="animax" start="20260105120000 +0800" stop="20260105130000 +0800">
    <title>Oshi No Ko</title>
  </programme>
  <programme channel="animax" start="20260105130000 +0800" stop="20260105140000 +0800">
    <title>D.Gray-Man (#53-103)</title>
  </programme>
  <programme channel="animax" start="20260105140000 +0800" stop="20260105150000 +0800">
    <title>Nyaight Of The Living Cat</title>
  </programme>
  <programme channel="animax" start="20260105150000 +0800" stop="20260105160000 +0800">
    <title>Wind Breaker</title>
  </programme>
  <programme channel="animax" start="20260105160000 +0800" stop="20260105170000 +0800">
    <title>D.Gray-Man (#53-103)</title>
  </programme>
  <programme channel="animax" start="20260105170000 +0800" stop="20260105180000 +0800">
    <title>Nyaight Of The Living Cat</title>
  </programme>
  <programme channel="animax" start="20260105180000 +0800" stop="20260105190000 +0800">
    <title>D.Gray-Man (#53-103)</title>
  </programme>
  <programme channel="animax" start="20260105190000 +0800" stop="20260105200000 +0800">
    <title>The Do-Over Damsel Conquers The Dragon Emperor</title>
  </programme>
  <programme channel="animax" start="20260105200000 +0800" stop="20260105210000 +0800">
    <title>The Red Ranger Becomes An Adventurer in Another World</title>
  </programme>
  <programme channel="animax" start="20260105210000 +0800" stop="20260105220000 +0800">
    <title>The Do-Over Damsel Conquers The Dragon Emperor</title>
  </programme>
  <programme channel="animax" start="20260105220000 +0800" stop="20260105230000 +0800">
    <title>The Foolish Angel Dances With The Devil</title>
  </programme>
  <programme channel="animax" start="20260105230000 +0800" stop="20260106000000 +0800">
    <title>The Do-Over Damsel Conquers The Dragon Emperor</title>
  </programme>
  <programme channel="animax" start="20260106000000 +0800" stop="20260106010000 +0800">
    <title>The Red Ranger Becomes An Adventurer in Another World</title>
  </programme>
  <programme channel="animax" start="20260106010000 +0800" stop="20260106020000 +0800">
    <title>The Foolish Angel Dances With The Devil</title>
  </programme>
  <programme channel="animax" start="20260106020000 +0800" stop="20260106030000 +0800">
    <title>D.Gray-Man (#53-103)</title>
  </programme>
  <programme channel="animax" start="20260106030000 +0800" stop="20260106040000 +0800">
    <title>The Red Ranger Becomes An Adventurer in Another World</title>
  </programme>
  <programme channel="animax" start="20260106040000 +0800" stop="20260106043000 +0800">
    <title>The Do-Over Damsel Conquers The Dragon Emperor</title>
  </programme>
  <programme channel="axn" start="20260105091500 +0800" stop="20260105101000 +0800">
    <title>Hudson &amp; Rex (Season 7)</title>
  </programme>
  <programme channel="axn" start="20260105101000 +0800" stop="20260105110000 +0800">
    <title>FBI (Season 6)</title>
  </programme>
  <programme channel="axn" start="20260105110000 +0800" stop="20260105115500 +0800">
    <title>Rookie Blue (Season 4)</title>
  </programme>
  <programme channel="axn" start="20260105115500 +0800" stop="20260105125000 +0800">
    <title>The Rookie (Season 7)</title>
  </programme>
  <programme channel="axn" start="20260105125000 +0800" stop="20260105134500 +0800">
    <title>Hudson &amp; Rex (Season 7)</title>
  </programme>
  <programme channel="axn" start="20260105134500 +0800" stop="20260105143500 +0800">
    <title>Blue Bloods (Season 14)</title>
  </programme>
  <programme channel="axn" start="20260105143500 +0800" stop="20260105153000 +0800">
    <title>Rookie Blue (Season 4)</title>
  </programme>
  <programme channel="axn" start="20260105153000 +0800" stop="20260105162500 +0800">
    <title>The Rookie (Season 7)</title>
  </programme>
  <programme channel="axn" start="20260105162500 +0800" stop="20260105171500 +0800">
    <title>FBI (Season 6)</title>
  </programme>
  <programme channel="axn" start="20260105171500 +0800" stop="20260105181000 +0800">
    <title>NCIS: Hawai'i (Season 3)</title>
  </programme>
  <programme channel="axn" start="20260105181000 +0800" stop="20260105190000 +0800">
    <title>FBI: Most Wanted (Season 6)</title>
  </programme>
  <programme channel="axn" start="20260105190000 +0800" stop="20260105195500 +0800">
    <title>Rookie Blue (Season 4)</title>
  </programme>
  <programme channel="axn" start="20260105195500 +0800" stop="20260105205000 +0800">
    <title>The Rookie (Season 7)</title>
  </programme>
  <programme channel="axn" start="20260105205000 +0800" stop="20260105214500 +0800">
    <title>The Rookie (Season 7)</title>
  </programme>
  <programme channel="axn" start="20260105214500 +0800" stop="20260105224000 +0800">
    <title>Boston Blue (Season 1)</title>
  </programme>
  <programme channel="axn" start="20260105224000 +0800" stop="20260105235000 +0800">
    <title>Twisted Metal (Season 1)</title>
  </programme>
  <programme channel="axn" start="20260105235000 +0800" stop="20260106004500 +0800">
    <title>Boston Blue (Season 1)</title>
  </programme>
  <programme channel="axn" start="20260106004500 +0800" stop="20260106013500 +0800">
    <title>The Rookie (Season 7)</title>
  </programme>
  <programme channel="axn" start="20260106013500 +0800" stop="20260106023000 +0800">
    <title>The Rookie (Season 7)</title>
  </programme>
  <programme channel="axn" start="20260106023000 +0800" stop="20260106032000 +0800">
    <title>FBI: Most Wanted (Season 6)</title>
  </programme>
  <programme channel="axn" start="20260106032000 +0800" stop="20260106035500 +0800">
    <title>Cyril: Simply Magic</title>
  </programme>
  <programme channel="axn" start="20260106035500 +0800" stop="20260106042500 +0800">
    <title>Twisted Metal (Season 1)</title>
  </programme>
  <programme channel="cinema-one" start="20260105100000 +0800" stop="20260105110000 +0800">
    <title>The B Side</title>
  </programme>
  <programme channel="cinema-one" start="20260105110000 +0800" stop="20260105130000 +0800">
    <title>Ala Eh Con Bisoy Hale Hale Hoy</title>
  </programme>
  <programme channel="cinema-one" start="20260105130000 +0800" stop="20260105150000 +0800">
    <title>Forever And A Day</title>
  </programme>
  <programme channel="cinema-one" start="20260105150000 +0800" stop="20260105170000 +0800">
    <title>D' Anothers</title>
  </programme>
  <programme channel="cinema-one" start="20260105170000 +0800" stop="20260105190000 +0800">
    <title>Fallback</title>
  </programme>
  <programme channel="cinema-one" start="20260105190000 +0800" stop="20260105210000 +0800">
    <title>Caregiver</title>
  </programme>
  <programme channel="cinema-one" start="20260105210000 +0800" stop="20260105230000 +0800">
    <title>Milan</title>
  </programme>
  <programme channel="cinema-one" start="20260105230000 +0800" stop="20260106010000 +0800">
    <title>Oda Sa Wala</title>
  </programme>
  <programme channel="cinema-one" start="20260106010000 +0800" stop="20260106030000 +0800">
    <title>Bad Girl</title>
  </programme>
  <programme channel="cinema-one" start="20260106030000 +0800" stop="20260106033000 +0800">
    <title>Kung Bakit Kita Minahal</title>
  </programme>
  <programme channel="gma" start="20260105093000 +0800" stop="20260105110000 +0800">
    <title>Kapuso Movie Festival</title>
  </programme>
  <programme channel="gma" start="20260105110000 +0800" stop="20260105120000 +0800">
    <title>Tiktoclock</title>
  </programme>
  <programme channel="gma" start="20260105120000 +0800" stop="20260105143000 +0800">
    <title>It's Showtime</title>
  </programme>
  <programme channel="gma" start="20260105143000 +0800" stop="20260105152000 +0800">
    <title>Hating Kapatid</title>
  </programme>
  <programme channel="gma" start="20260105152000 +0800" stop="20260105160500 +0800">
    <title>Cruz vs. Cruz</title>
  </programme>
  <programme channel="gma" start="20260105160500 +0800" stop="20260105163000 +0800">
    <title>Fast Talk with Boy Abunda</title>
  </programme>
  <programme channel="gma" start="20260105163000 +0800" stop="20260105171000 +0800">
    <title>Unica Hija</title>
  </programme>
  <programme channel="gma" start="20260105171000 +0800" stop="20260105174000 +0800">
    <title>You Are My Make-Up Artist</title>
  </programme>
  <programme channel="gma" start="20260105174000 +0800" stop="20260105183000 +0800">
    <title>Family Feud</title>
  </programme>
  <programme channel="gma" start="20260105183000 +0800" stop="20260105200500 +0800">
    <title>24 Oras</title>
  </programme>
  <programme channel="gma" start="20260105200500 +0800" stop="20260105205500 +0800">
    <title>Encantadia Chronicles: Sang'gre</title>
  </programme>
  <programme channel="gma" start="20260105205500 +0800" stop="20260105214000 +0800">
    <title>Sanggang - Dikit FR</title>
  </programme>
  <programme channel="gma" start="20260105214000 +0800" stop="20260105222000 +0800">
    <title>Pinoy Big Brother Collab Edition 2.0</title>
  </programme>
  <programme channel="gma" start="20260105222000 +0800" stop="20260105230000 +0800">
    <title>Saksi</title>
  </programme>
  <programme channel="gma" start="20260105230000 +0800" stop="20260105233000 +0800">
    <title>When I Marry A Stranger</title>
  </programme>
  <programme channel="gma" start="20260105233000 +0800" stop="20260106000000 +0800">
    <title>To The Moon and Back</title>
  </programme>
  <programme channel="gma" start="20260106000000 +0800" stop="20260106003000 +0800">
    <title>The 700 Club Asia</title>
  </programme>
  <programme channel="gtv" start="20260105090000 +0800" stop="20260105110000 +0800">
    <title>Cinema G!</title>
  </programme>
  <programme channel="gtv" start="20260105110000 +0800" stop="20260105120000 +0800">
    <title>Balitanghali</title>
  </programme>
  <programme channel="gtv" start="20260105120000 +0800" stop="20260105143000 +0800">
    <title>Noontime Movie Hits</title>
  </programme>
  <programme channel="gtv" start="20260105143000 +0800" stop="20260105150000 +0800">
    <title>One The Woman</title>
  </programme>
  <programme channel="gtv" start="20260105150000 +0800" stop="20260105153000 +0800">
    <title>The Skywatcher</title>
  </programme>
  <programme channel="gtv" start="20260105153000 +0800" stop="20260105174500 +0800">
    <title>Afternoon Movie Break</title>
  </programme>
  <programme channel="gtv" start="20260105174500 +0800" stop="20260105183000 +0800">
    <title>Heartful Cafe</title>
  </programme>
  <programme channel="gtv" start="20260105183000 +0800" stop="20260105200500 +0800">
    <title>24 Oras</title>
  </programme>
  <programme channel="gtv" start="20260105200500 +0800" stop="20260105214500 +0800">
    <title>G! Flicks</title>
  </programme>
  <programme channel="gtv" start="20260105214500 +0800" stop="20260105223000 +0800">
    <title>Encantadia Chronicles: Sang'gre</title>
  </programme>
  <programme channel="gtv" start="20260105223000 +0800" stop="20260105230000 +0800">
    <title>Sanggang - Dikit FR</title>
  </programme>
  <programme channel="gtv" start="20260105230000 +0800" stop="20260105232500 +0800">
    <title>State Of The Nation</title>
  </programme>
  <programme channel="gtv" start="20260105232500 +0800" stop="20260105235500 +0800">
    <title>True Horror Stories</title>
  </programme>
  <programme channel="ibc-tv-13" start="20260105100000 +0800" stop="20260105120000 +0800">
    <title>#IPABITAGMO - Sumbungan Ng Sambayanan</title>
  </programme>
  <programme channel="ibc-tv-13" start="20260105120000 +0800" stop="20260105123000 +0800">
    <title>PBBM - RTVM</title>
  </programme>
  <programme channel="ibc-tv-13" start="20260105123000 +0800" stop="20260105130000 +0800">
    <title>Congress TV</title>
  </programme>
  <programme channel="ibc-tv-13" start="20260105130000 +0800" stop="20260105140000 +0800">
    <title>AlaUna Sa Balita</title>
  </programme>
  <programme channel="ibc-tv-13" start="20260105140000 +0800" stop="20260105141500 +0800">
    <title>PCSO Lottery Draw</title>
  </programme>
  <programme channel="ibc-tv-13" start="20260105141500 +0800" stop="20260105143000 +0800">
    <title>PBBM - RTVM</title>
  </programme>
  <programme channel="ibc-tv-13" start="20260105143000 +0800" stop="20260105150000 +0800">
    <title>Sharing ASEAN</title>
  </programme>
  <programme channel="ibc-tv-13" start="20260105150000 +0800" stop="20260105160000 +0800">
    <title>PBBM - RTVM</title>
  </programme>
  <programme channel="ibc-tv-13" start="20260105160000 +0800" stop="20260105170000 +0800">
    <title>IBC Tutok 13</title>
  </programme>
  <programme channel="ibc-tv-13" start="20260105170000 +0800" stop="20260105171500 +0800">
    <title>PCSO Lottery Draw</title>
  </programme>
  <programme channel="ibc-tv-13" start="20260105171500 +0800" stop="20260105173000 +0800">
    <title>Faces Of ASEAN</title>
  </programme>
  <programme channel="ibc-tv-13" start="20260105173000 +0800" stop="20260105180000 +0800">
    <title>Congress News</title>
  </programme>
  <programme channel="ibc-tv-13" start="20260105180000 +0800" stop="20260105183000 +0800">
    <title>Colors Of ASEAN</title>
  </programme>
  <programme channel="ibc-tv-13" start="20260105183000 +0800" stop="20260105190000 +0800">
    <title>PBBM - RTVM</title>
  </programme>
  <programme channel="ibc-tv-13" start="20260105190000 +0800" stop="20260105191000 +0800">
    <title>IBC Express Balita</title>
  </programme>
  <programme channel="ibc-tv-13" start="20260105191000 +0800" stop="20260105200000 +0800">
    <title>Congress TV</title>
  </programme>
  <programme channel="ibc-tv-13" start="20260105200000 +0800" stop="20260105201000 +0800">
    <title>IBC Express Balita</title>
  </programme>
  <programme channel="ibc-tv-13" start="20260105201000 +0800" stop="20260105210000 +0800">
    <title>PBBM - RTVM</title>
  </programme>
  <programme channel="ibc-tv-13" start="20260105210000 +0800" stop="20260105213000 +0800">
    <title>PCSO Lottery Draw</title>
  </programme>
  <programme channel="ibc-tv-13" start="20260105213000 +0800" stop="20260105220000 +0800">
    <title>PBBM - RTVM</title>
  </programme>
  <programme channel="ibc-tv-13" start="20260105220000 +0800" stop="20260105223000 +0800">
    <title>Ang Senado Ng Pilipinas</title>
  </programme>
  <programme channel="jeepney-tv" start="20260105100000 +0800" stop="20260105110000 +0800">
    <title>Annaliza</title>
  </programme>
  <programme channel="jeepney-tv" start="20260105110000 +0800" stop="20260105120000 +0800">
    <title>Ikaw Ay Pag-Ibig</title>
  </programme>
  <programme channel="jeepney-tv" start="20260105120000 +0800" stop="20260105130000 +0800">
    <title>Dahil May Isang Ikaw</title>
  </programme>
  <programme channel="jeepney-tv" start="20260105130000 +0800" stop="20260105140000 +0800">
    <title>Rosalka</title>
  </programme>
  <programme channel="jeepney-tv" start="20260105140000 +0800" stop="20260105143000 +0800">
    <title>Kahit Puso'y Masugatan</title>
  </programme>
  <programme channel="jeepney-tv" start="20260105143000 +0800" stop="20260105150000 +0800">
    <title>Walang Hanggan</title>
  </programme>
  <programme channel="jeepney-tv" start="20260105150000 +0800" stop="20260105154500 +0800">
    <title>Maging Sino ka Man: Ang Pagbabalik</title>
  </programme>
  <programme channel="jeepney-tv" start="20260105154500 +0800" stop="20260105164500 +0800">
    <title>Apoy Sa Dagat</title>
  </programme>
  <programme channel="jeepney-tv" start="20260105164500 +0800" stop="20260105173000 +0800">
    <title>Basta't Kasama Kita</title>
  </programme>
  <programme channel="jeepney-tv" start="20260105173000 +0800" stop="20260105174500 +0800">
    <title>TV Patrol Express</title>
  </programme>
  <programme channel="jeepney-tv" start="20260105174500 +0800" stop="20260105183000 +0800">
    <title>PHR: Paraiso</title>
  </programme>
  <programme channel="jeepney-tv" start="20260105183000 +0800" stop="20260105193000 +0800">
    <title>The Promise Of Forever</title>
  </programme>
  <programme channel="jeepney-tv" start="20260105193000 +0800" stop="20260105200000 +0800">
    <title>Kung Ako'y Iiwan Mo</title>
  </programme>
  <programme channel="jeepney-tv" start="20260105200000 +0800" stop="20260105204500 +0800">
    <title>The Blood Sisters</title>
  </programme>
  <programme channel="jeepney-tv" start="20260105204500 +0800" stop="20260105213000 +0800">
    <title>Pusong Ligaw</title>
  </programme>
  <programme channel="jeepney-tv" start="20260105213000 +0800" stop="20260105221500 +0800">
    <title>Ang Sa Iyo Ay Akin</title>
  </programme>
  <programme channel="jeepney-tv" start="20260105221500 +0800" stop="20260105230500 +0800">
    <title>Roja</title>
  </programme>
  <programme channel="jeepney-tv" start="20260105230500 +0800" stop="20260105233500 +0800">
    <title>What Lies Beneath</title>
  </programme>
  <programme channel="jeepney-tv" start="20260105233500 +0800" stop="20260106000000 +0800">
    <title>PHR: Paraiso</title>
  </programme>
  <programme channel="jeepney-tv" start="20260106000000 +0800" stop="20260106004500 +0800">
    <title>Kung Ako'y Iiwan Mo</title>
  </programme>
  <programme channel="jeepney-tv" start="20260106004500 +0800" stop="20260106012000 +0800">
    <title>Basta't Kasama Kita</title>
  </programme>
  <programme channel="jeepney-tv" start="20260106012000 +0800" stop="20260106020000 +0800">
    <title>Maging Sino ka Man: Ang Pagbabalik</title>
  </programme>
  <programme channel="jeepney-tv" start="20260106020000 +0800" stop="20260106024500 +0800">
    <title>Pusong Ligaw</title>
  </programme>
  <programme channel="jeepney-tv" start="20260106024500 +0800" stop="20260106033000 +0800">
    <title>Ang Sa Iyo Ay Akin</title>
  </programme>
  <programme channel="jeepney-tv" start="20260106033000 +0800" stop="20260106044500 +0800">
    <title>Apoy Sa Dagat</title>
  </programme>
  <programme channel="jeepney-tv" start="20260106044500 +0800" stop="20260106051500 +0800">
    <title>Kung Ako'y Iiwan Mo</title>
  </programme>
  <programme channel="kapamilya-channel" start="20260105100000 +0800" stop="20260105120000 +0800">
    <title>Kapamilya Blockbusters</title>
  </programme>
  <programme channel="kapamilya-channel" start="20260105120000 +0800" stop="20260105143000 +0800">
    <title>It's Showtime</title>
  </programme>
  <programme channel="kapamilya-channel" start="20260105143000 +0800" stop="20260105151500 +0800">
    <title>Lavender Fields</title>
  </programme>
  <programme channel="kapamilya-channel" start="20260105151500 +0800" stop="20260105160000 +0800">
    <title>Senior High</title>
  </programme>
  <programme channel="kapamilya-channel" start="20260105160000 +0800" stop="20260105173000 +0800">
    <title>Kapamilya Gold Hits</title>
  </programme>
  <programme channel="kapamilya-channel" start="20260105173000 +0800" stop="20260105174500 +0800">
    <title>TV Patrol Express</title>
  </programme>
  <programme channel="kapamilya-channel" start="20260105174500 +0800" stop="20260105183000 +0800">
    <title>Kapamilya Deal Or No Deal</title>
  </programme>
  <programme channel="kapamilya-channel" start="20260105183000 +0800" stop="20260105200000 +0800">
    <title>TV Patrol</title>
  </programme>
  <programme channel="kapamilya-channel" start="20260105200000 +0800" stop="20260105204500 +0800">
    <title>FPJ's Batang Quiapo</title>
  </programme>
  <programme channel="kapamilya-channel" start="20260105204500 +0800" stop="20260105213000 +0800">
    <title>Roja</title>
  </programme>
  <programme channel="kapamilya-channel" start="20260105213000 +0800" stop="20260105221500 +0800">
    <title>What Lies Beneath</title>
  </programme>
  <programme channel="kapamilya-channel" start="20260105221500 +0800" stop="20260105224500 +0800">
    <title>Go Ahead</title>
  </programme>
  <programme channel="kapamilya-channel" start="20260105224500 +0800" stop="20260105231500 +0800">
    <title>The World Tonight</title>
  </programme>
  <programme channel="kapamilya-channel" start="20260105231500 +0800" stop="20260106020000 +0800">
    <title>Movie Central Presents</title>
  </programme>
  <programme channel="kapamilya-channel" start="20260106020000 +0800" stop="20260106034500 +0800">
    <title>Movie Central Presents</title>
  </programme>
  <programme channel="kapamilya-channel" start="20260106034500 +0800" stop="20260106041500 +0800">
    <title>Movie Central Presents</title>
  </programme>
  <programme channel="net-25" start="20260105100000 +0800" stop="20260105120000 +0800">
    <title>Kada Umaga</title>
  </programme>
  <programme channel="net-25" start="20260105120000 +0800" stop="20260105123000 +0800">
    <title>Mata Ng Agila Sa Tanghali</title>
  </programme>
  <programme channel="net-25" start="20260105123000 +0800" stop="20260105130000 +0800">
    <title>Love Me, Love My Voice</title>
  </programme>
  <programme channel="net-25" start="20260105130000 +0800" stop="20260105133000 +0800">
    <title>Love Designer</title>
  </programme>
  <programme channel="net-25" start="20260105133000 +0800" stop="20260105140000 +0800">
    <title>Strict Ang Mommy Ko</title>
  </programme>
  <programme channel="net-25" start="20260105140000 +0800" stop="20260105143000 +0800">
    <title>Rising with the Wind</title>
  </programme>
  <programme channel="net-25" start="20260105143000 +0800" stop="20260105150000 +0800">
    <title>A Date With The Future</title>
  </programme>
  <programme channel="net-25" start="20260105150000 +0800" stop="20260105160000 +0800">
    <title>Oh No, Its B.O.!</title>
  </programme>
  <programme channel="net-25" start="20260105160000 +0800" stop="20260105163000 +0800">
    <title>Road to Starkada</title>
  </programme>
  <programme channel="net-25" start="20260105163000 +0800" stop="20260105180000 +0800">
    <title>Sa Ganang Mamamayan</title>
  </programme>
  <programme channel="net-25" start="20260105180000 +0800" stop="20260105193000 +0800">
    <title>Mata Ng Agila</title>
  </programme>
  <programme channel="net-25" start="20260105193000 +0800" stop="20260105200000 +0800">
    <title>Best Choice Ever</title>
  </programme>
  <programme channel="net-25" start="20260105200000 +0800" stop="20260105203000 +0800">
    <title>Go Go Squid</title>
  </programme>
  <programme channel="net-25" start="20260105203000 +0800" stop="20260105210000 +0800">
    <title>A Date With The Future</title>
  </programme>
  <programme channel="net-25" start="20260105210000 +0800" stop="20260105213000 +0800">
    <title>As Beautiful As You</title>
  </programme>
  <programme channel="net-25" start="20260105213000 +0800" stop="20260105223000 +0800">
    <title>Mata Ng Agila International</title>
  </programme>
  <programme channel="net-25" start="20260105223000 +0800" stop="20260105230000 +0800">
    <title>REV</title>
  </programme>
  <programme channel="net-25" start="20260105230000 +0800" stop="20260105233000 +0800">
    <title>In Good Shape</title>
  </programme>
  <programme channel="net-25" start="20260105233000 +0800" stop="20260106000000 +0800">
    <title>Tomorrow Today</title>
  </programme>
  <programme channel="net-25" start="20260106000000 +0800" stop="20260106003000 +0800">
    <title>See For Yourself</title>
  </programme>
  <programme channel="net-25" start="20260106003000 +0800" stop="20260106010000 +0800">
    <title>Kini Ang Kamatuoran</title>
  </programme>
  <programme channel="net-25" start="20260106010000 +0800" stop="20260106013000 +0800">
    <title>INC international Edition</title>
  </programme>
  <programme channel="net-25" start="20260106013000 +0800" stop="20260106020000 +0800">
    <title>Gabay Sa Mabuting Asal</title>
  </programme>
  <programme channel="net-25" start="20260106020000 +0800" stop="20260106023000 +0800">
    <title>Executive News Feature</title>
  </programme>
  <programme channel="net-25" start="20260106023000 +0800" stop="20260106033000 +0800">
    <title>Landas Ng Buhay</title>
  </programme>
  <programme channel="net-25" start="20260106033000 +0800" stop="20260106040000 +0800">
    <title>Turning Point</title>
  </programme>
  <programme channel="net-25" start="20260106040000 +0800" stop="20260106043000 +0800">
    <title>#Panatag</title>
  </programme>
  <programme channel="net-25" start="20260106043000 +0800" stop="20260106050000 +0800">
    <title>Lingap Stories</title>
  </programme>
  <programme channel="pbo" start="20260105091500 +0800" stop="20260105111500 +0800">
    <title>Elevator</title>
  </programme>
  <programme channel="pbo" start="20260105111500 +0800" stop="20260105131500 +0800">
    <title>Ikaw na Sana</title>
  </programme>
  <programme channel="pbo" start="20260105131500 +0800" stop="20260105151500 +0800">
    <title>Honey My Love So Sweet</title>
  </programme>
  <programme channel="pbo" start="20260105151500 +0800" stop="20260105173000 +0800">
    <title>Sanggano't Sanggago</title>
  </programme>
  <programme channel="pbo" start="20260105173000 +0800" stop="20260105193000 +0800">
    <title>Ang Cute Ng Ina Mo</title>
  </programme>
  <programme channel="pbo" start="20260105193000 +0800" stop="20260105213000 +0800">
    <title>Biyernes Santo</title>
  </programme>
  <programme channel="pbo" start="20260105213000 +0800" stop="20260105233000 +0800">
    <title>Hitman</title>
  </programme>
  <programme channel="pbo" start="20260105233000 +0800" stop="20260106013000 +0800">
    <title>Warat</title>
  </programme>
  <programme channel="pbo" start="20260106013000 +0800" stop="20260106033000 +0800">
    <title>Pagnanasa</title>
  </programme>
  <programme channel="pbo" start="20260106033000 +0800" stop="20260106040000 +0800">
    <title>Nag-aapoy Na Langit</title>
  </programme>
  <programme channel="ptv" start="20260105100000 +0800" stop="20260105110000 +0800">
    <title>Radyo Publiko Serbisyo</title>
  </programme>
  <programme channel="ptv" start="20260105110000 +0800" stop="20260105120000 +0800">
    <title>In Person</title>
  </programme>
  <programme channel="ptv" start="20260105120000 +0800" stop="20260105130000 +0800">
    <title>Bagong Pilipinas Ngayon</title>
  </programme>
  <programme channel="ptv" start="20260105130000 +0800" stop="20260105140000 +0800">
    <title>Sentro Balita</title>
  </programme>
  <programme channel="ptv" start="20260105140000 +0800" stop="20260105141500 +0800">
    <title>ASEAN Documentary</title>
  </programme>
  <programme channel="ptv" start="20260105141500 +0800" stop="20260105150000 +0800">
    <title>Stories From The Grid</title>
  </programme>
  <programme channel="ptv" start="20260105150000 +0800" stop="20260105160000 +0800">
    <title>PTV Sports</title>
  </programme>
  <programme channel="ptv" start="20260105160000 +0800" stop="20260105170000 +0800">
    <title>Kangrunaan A Damag</title>
  </programme>
  <programme channel="ptv" start="20260105170000 +0800" stop="20260105180000 +0800">
    <title>PTV News Mindanao</title>
  </programme>
  <programme channel="ptv" start="20260105180000 +0800" stop="20260105190000 +0800">
    <title>Ulat Bayan</title>
  </programme>
  <programme channel="ptv" start="20260105190000 +0800" stop="20260105200000 +0800">
    <title>On Assignment</title>
  </programme>
  <programme channel="ptv" start="20260105200000 +0800" stop="20260105210000 +0800">
    <title>Pag-usapan Natin with Oscar Orbos</title>
  </programme>
  <programme channel="ptv" start="20260105210000 +0800" stop="20260105220000 +0800">
    <title>PTV News Tonight</title>
  </programme>
  <programme channel="ptv" start="20260105220000 +0800" stop="20260105230000 +0800">
    <title>Oras Ng Himala</title>
  </programme>
  <programme channel="ptv" start="20260105230000 +0800" stop="20260105233000 +0800">
    <title>Bagong Pilipinas Ngayon</title>
  </programme>
  <programme channel="solar-flix" start="20260105100000 +0800" stop="20260105110000 +0800">
    <title>Forbidden Fruit S2</title>
  </programme>
  <programme channel="solar-flix" start="20260105110000 +0800" stop="20260105120000 +0800">
    <title>In Between</title>
  </programme>
  <programme channel="solar-flix" start="20260105120000 +0800" stop="20260105130000 +0800">
    <title>Recipes Of Love</title>
  </programme>
  <programme channel="solar-flix" start="20260105130000 +0800" stop="20260105133000 +0800">
    <title>I Want To Be</title>
  </programme>
  <programme channel="solar-flix" start="20260105133000 +0800" stop="20260105140000 +0800">
    <title>Marimar</title>
  </programme>
  <programme channel="solar-flix" start="20260105140000 +0800" stop="20260105160000 +0800">
    <title>Ang Titser Kong Pogi</title>
  </programme>
  <programme channel="solar-flix" start="20260105160000 +0800" stop="20260105170000 +0800">
    <title>Forbidden Fruit S2</title>
  </programme>
  <programme channel="solar-flix" start="20260105170000 +0800" stop="20260105180000 +0800">
    <title>In Between</title>
  </programme>
  <programme channel="solar-flix" start="20260105180000 +0800" stop="20260105190000 +0800">
    <title>Secret Of Feriha The Untold Story</title>
  </programme>
  <programme channel="solar-flix" start="20260105190000 +0800" stop="20260105210000 +0800">
    <title>Kalibre 45</title>
  </programme>
  <programme channel="solar-flix" start="20260105210000 +0800" stop="20260105220000 +0800">
    <title>Secret Of Feriha The Untold Story</title>
  </programme>
  <programme channel="solar-flix" start="20260105220000 +0800" stop="20260106000000 +0800">
    <title>Sugat Sa Puri</title>
  </programme>
  <programme channel="solar-flix" start="20260106000000 +0800" stop="20260106010000 +0800">
    <title>Forbidden Fruit S2</title>
  </programme>
  <programme channel="solar-flix" start="20260106010000 +0800" stop="20260106020000 +0800">
    <title>In Between</title>
  </programme>
  <programme channel="solar-flix" start="20260106020000 +0800" stop="20260106040000 +0800">
    <title>Shirley</title>
  </programme>
  <programme channel="solar-flix" start="20260106040000 +0800" stop="20260106043000 +0800">
    <title>The Girl King</title>
  </programme>
  <programme channel="tv5" start="20260105090000 +0800" stop="20260105103000 +0800">
    <title>Cine Cinco Sa Umaga</title>
  </programme>
  <programme channel="tv5" start="20260105103000 +0800" stop="20260105110000 +0800">
    <title>Frontline Express Live</title>
  </programme>
  <programme channel="tv5" start="20260105110000 +0800" stop="20260105120000 +0800">
    <title>Face 2 Face Harapan</title>
  </programme>
  <programme channel="tv5" start="20260105120000 +0800" stop="20260105143000 +0800">
    <title>Eat Bulaga</title>
  </programme>
  <programme channel="tv5" start="20260105143000 +0800" stop="20260105151000 +0800">
    <title>Frontline Express Live</title>
  </programme>
  <programme channel="tv5" start="20260105151000 +0800" stop="20260105164500 +0800">
    <title>Cine Cinco Sa Hapon</title>
  </programme>
  <programme channel="tv5" start="20260105164500 +0800" stop="20260105190000 +0800">
    <title>Vibe Up!</title>
  </programme>
  <programme channel="tv5" start="20260105190000 +0800" stop="20260105224500 +0800">
    <title>Totoy Bato</title>
  </programme>
  <programme channel="tv5" start="20260105224500 +0800" stop="20260105233000 +0800">
    <title>Frontline Tonight</title>
  </programme>
  <programme channel="tv5" start="20260105233000 +0800" stop="20260106000000 +0800">
    <title>Vibe Nights</title>
  </programme>
  <programme channel="tv5" start="20260106000000 +0800" stop="20260106043000 +0800">
    <title>Oras Ng Himala</title>
  </programme>
  <programme channel="tv5" start="20260106043000 +0800" stop="20260106050000 +0800">
    <title>Word Of God</title>
  </programme>
  <programme channel="viva-cinema" start="20260105100000 +0800" stop="20260105120000 +0800">
    <title>SP04 Santiago Sharp Shooter</title>
  </programme>
  <programme channel="viva-cinema" start="20260105120000 +0800" stop="20260105141500 +0800">
    <title>Judge Max Asuncion, Hukom Bitay</title>
  </programme>
  <programme channel="viva-cinema" start="20260105141500 +0800" stop="20260105161500 +0800">
    <title>Extranghero</title>
  </programme>
  <programme channel="viva-cinema" start="20260105161500 +0800" stop="20260105181500 +0800">
    <title>Markadong Hudas</title>
  </programme>
  <programme channel="viva-cinema" start="20260105181500 +0800" stop="20260105201500 +0800">
    <title>April Boys Sana'y Mahalin Mo Rin Ako</title>
  </programme>
  <programme channel="viva-cinema" start="20260105201500 +0800" stop="20260105221500 +0800">
    <title>Tootsie Wootsie</title>
  </programme>
  <programme channel="viva-cinema" start="20260105221500 +0800" stop="20260106000000 +0800">
    <title>Magkapalad</title>
  </programme>
  <programme channel="viva-cinema" start="20260106000000 +0800" stop="20260106020000 +0800">
    <title>Brando Bandido</title>
  </programme>
  <programme channel="viva-cinema" start="20260106020000 +0800" stop="20260106040000 +0800">
    <title>Blondie</title>
  </programme>
  <programme channel="viva-cinema" start="20260106040000 +0800" stop="20260106043000 +0800">
    <title>Simaron</title>
  </programme>
</tv>
